{
  "timestamp": "2026-01-13T20:55:00",
  "device": "Jetson Orin Nano",
  "method": "3-tier (GPU + DRAM + Storage)",
  "gpu_chunk_qubits": 22,
  "max_qubits": 29,
  "results": [
    {
      "qubits": 28,
      "hilbert_dim": 268435456,
      "storage_gb": 2.0,
      "init_time_s": 63.83,
      "gate_time_s": 164.09,
      "io_total_gb": 12.0,
      "norm": 1.0,
      "success": true
    },
    {
      "qubits": 29,
      "hilbert_dim": 536870912,
      "storage_gb": 4.0,
      "init_time_s": 135.6,
      "gate_time_s": 351.6,
      "io_total_gb": 24.0,
      "norm": 1.0,
      "success": true
    }
  ]
}
